[{"created_at":"2015-09-12T18:47:48Z","text":"Cerruti Boxershorts in Farbset nach Wahl (67% sparen*) (19 99 € statt 59 98 €) http://t.co/KzTKS8VWgT #schnäppchen #deal #dealz #sparen #…","lang":"de","tweet_hashtags":["schnäppchen","deal","dealz","sparen"],"tweet_urls":["http://ift.tt/1LqtfR6"]},{"created_at":"2015-09-12T18:47:52Z","text":"Wellnessa Boxspringmatratze Duo-Comfort in der Größe nach Wahl mit 5 cm Topper inkl. Versand (bis zu 84% sparen) (229 € statt 1.399 €) …","lang":"de","tweet_hashtags":["schnäppchen","deal","dealz","sparen"],"tweet_urls":["http://ift.tt/1LqtfR6"]},{"created_at":"2015-09-12T18:47:53Z","text":"6 Bausch \u0026amp; Lomb Monatslinsen SofLens 59 weich in der Stärke nach Wahl für 14 99 € (50% sparen*) (14 99 € statt 29 90 €) …","lang":"de","tweet_hashtags":["schnäppchen","deal","dealz","sparen"],"tweet_urls":["http://ift.tt/1LqtfR6"]},{"created_at":"2015-09-12T18:49:26Z","text":"Wenn du jemanden vor die Wahl stellst  du oder eine andere  ihm wichtige  Person  bedeutet das nur  dass du bereit bist  ihn zu verlieren.","lang":"de","tweet_hashtags":["политика"],"tweet_urls":["http://top.rbc.ru/politics/12/09/2015/55f425e29a794780d0a3d45c","http://vesti-ukr.com/mir/40862-putin-nazval-vlast-v-ukraine-nelegitimnoj"]},{"created_at":"2015-09-12T18:51:33Z","text":"@hntngprty glücklicherweise eine Sprache  die ich ignoriert habe ^^ Manchmal ist neu programmieren die bessere Wahl.","lang":"de","tweet_hashtags":["Russian"],"tweet_urls":["http://news.google.com/news/url?sa\u003dt\u0026fd\u003dR\u0026ct2\u003dru_ru\u0026usg\u003dAFQjCNEE4jzGD43Hp5ufXY-cEoIqp1ZoIg\u0026clid\u003dc3a7d30bb8a4878e06b80cf16b898331\u0026cid\u003d52779463735397\u0026ei\u003dPaz0VfjMA92-4AKCiKvQCg\u0026url\u003dhttp://ria.ru/politics/20150913/1247525159.html"]},{"created_at":"2015-09-12T19:00:11Z","text":"15er-Pack bruno banani Sneakersocken in der Größe nach Wahl (80% sparen*) http://t.co/7Fz3JFPZVb","lang":"de","tweet_hashtags":["Политика","ВМире"],"tweet_urls":["http://tinyurl.com/q2yapb6"]},{"created_at":"2015-09-12T19:01:49Z","text":"Donald trump war gerade bei schlag den raab xD","lang":"de","tweet_hashtags":["украина","война","прогноз","политика"],"tweet_urls":["http://top.rbc.ru/politics/12/09/2015/55f425e29a794780d0a3d45c","http://vesti-ukr.com/mir/40862-putin-nazval-vlast-v-ukraine-nelegitimnoj"]},{"created_at":"2015-09-12T19:02:10Z","text":"Donald Trump. Gätjen: \"Eventuell bald US Präsident.\" 😂 \n#SdR","lang":"de","tweet_hashtags":["SdR"],"tweet_urls":["http://top.rbc.ru/politics/12/09/2015/55f425e29a794780d0a3d45c","http://vesti-ukr.com/mir/40862-putin-nazval-vlast-v-ukraine-nelegitimnoj"]},{"created_at":"2015-09-12T19:02:30Z","text":"Cerruti Boxershorts in Farbset nach Wahl (67% sparen*) (19 99 € statt 59 98 €) http://t.co/kvrmuUiLqG #schnäppchen #deal #dealz #sparen #…","lang":"de","tweet_hashtags":["schnäppchen","deal","dealz","sparen"],"tweet_urls":["http://ift.tt/1L95uRO"]},{"created_at":"2015-09-12T19:02:35Z","text":"Wellnessa Boxspringmatratze Duo-Comfort in der Größe nach Wahl mit 5 cm Topper inkl. Versand (bis zu 84% sparen) (229 € statt 1.399 €) …","lang":"de","tweet_hashtags":["schnäppchen","deal","dealz","sparen"],"tweet_urls":["http://ift.tt/1L95uRO"]},{"created_at":"2015-09-12T19:02:37Z","text":"6 Bausch \u0026amp; Lomb Monatslinsen SofLens 59 weich in der Stärke nach Wahl für 14 99 € (50% sparen*) (14 99 € statt 29 90 €) …","lang":"de","tweet_hashtags":["schnäppchen","deal","dealz","sparen"],"tweet_urls":["http://ift.tt/1L95uRO"]},{"created_at":"2015-09-12T19:02:44Z","text":"\"Donald Trump  der Mann mit der Beton Frisur.\" #SdR \n\nNenenene dieser Titel gehört @PietSmiet","lang":"de","tweet_hashtags":["SdR"],"tweet_urls":["http://bit.ly/1XXNHlV"]},{"created_at":"2015-09-12T19:06:09Z","text":"Gewinne die Razer Deathstalker \u0026amp; Deathadder Chroma + 5 Games nach Wahl via  http://t.co/Y0QJdWLeb2","lang":"de","tweet_hashtags":["яндекс","yandex","новости","политика","культура","общество"],"tweet_urls":["http://virl.io/HxNnhHmJ"]},{"created_at":"2015-09-12T19:17:08Z","text":"Wenn ich die Wahl zwischen Schmerz und nichts hätte  würde ich den Schmerz nehmen  denn dann wüsste ich zumindest  dass ich noch existiere.","lang":"de","tweet_hashtags":["выборы"],"tweet_urls":["http://top.rbc.ru/politics/12/09/2015/55f425e29a794780d0a3d45c","http://vesti-ukr.com/mir/40862-putin-nazval-vlast-v-ukraine-nelegitimnoj"]},{"created_at":"2015-09-12T19:18:10Z","text":"@rwolupo PS.: Bei der letzten Wahl gab es sogar meine Zweitstimme für die Piraten. Nun würde ich nicht meine Stimme für Dummköpfe geben!","lang":"de","tweet_hashtags":["новости"],"tweet_urls":["http://bit.ly/1OLujSO"]},{"created_at":"2015-09-12T19:18:23Z","text":"Wellnessa Boxspringmatratze Duo-Comfort in der Größe nach Wahl mit 5 cm Topper inkl. Versand (bis zu 84% sparen) (229 € statt 1.399 €) …","lang":"de","tweet_hashtags":["новости"],"tweet_urls":["http://www.mk.ru/politics/2015/09/12/rukovoditeli-diplomaticheskikh-vedomstv-normandskoy-chetverki-zakonchili-peregovory.html"]},{"created_at":"2015-09-12T19:18:23Z","text":"TV-Sideboard Samuel in Farbe und Länge nach Wahl inkl. Versand (bis zu 53% sparen) (99 € statt 199 €) http://t.co/HpUijPfqd9 #schnäppchen…","lang":"de","tweet_hashtags":["schnäppchen"],"tweet_urls":["http://ift.tt/1K6eSnb"]},{"created_at":"2015-09-12T19:24:52Z","text":"Die meisten bürgerlichen Politiker/Innen \nim Bundestag in Berlin vergessen sofort \nnach ihrer Wahl ihr Wahlversprechen.\nIst das etwa Demenz?","lang":"de","tweet_hashtags":["Выборы","НН"],"tweet_urls":["http://zn.ua/POLITICS/normandskaya-vstrecha-klimkin-nazval-peregovory-tradicionno-tyazhelymi-188508_.html"]},{"created_at":"2015-09-12T19:28:07Z","text":"Wahl Lithium Ion Trimmer Kit 17 Pieces Model 9854-600 http://t.co/otVxT5Yg7v http://t.co/HAsa7m0rs0","lang":"de","tweet_hashtags":["Лада"],"tweet_urls":["http://www.ebay.com/itm/221882769788?ssPageName\u003dSTRK:MESELX:IT\u0026_trksid\u003dp3984.m1555.l2649"]}]